positron/__init__.py
positron/app.py
positronpy-0.18.dist-info/LICENSE
positronpy-0.18.dist-info/METADATA
positronpy-0.18.dist-info/WHEEL
positronpy-0.18.dist-info/entry_points.txt
positronpy-0.18.dist-info/top_level.txt
positronpy-0.18.dist-info/RECORD
