Metadata-Version: 2.1
Name: positronpy
Version: 0.18
Summary: Build desktop apps with Python
Author-email: Kaan Giray Buzluk <kaangiray26@protonmail.com>
License: MIT License
Project-URL: Homepage, https://github.com/kaangiray26/positron
Project-URL: Bug Tracker, https://github.com/kaangiray26/positron/issues
Classifier: Programming Language :: Python :: 3
Classifier: License :: OSI Approved :: GNU General Public License v3 (GPLv3)
Classifier: Operating System :: OS Independent
Requires-Python: >=3.8
License-File: LICENSE
Requires-Dist: requests
Requires-Dist: pyyaml
